<PAMDataset>
  <PAMRasterBand band="1">
    <Histograms>
      <HistItem>
        <HistMin>35.57047486819432</HistMin>
        <HistMax>36.59428184965763</HistMax>
        <BucketCount>1000</BucketCount>
        <IncludeOutOfRange>0</IncludeOutOfRange>
        <Approximate>0</Approximate>
        <HistCounts>100|0|0|0|0|0|0|0|0|0|0|100|0|0|0|0|0|0|0|0|0|0|0|100|0|0|0|0|0|0|0|0|0|0|100|0|0|0|0|0|0|0|0|0|0|100|0|0|0|0|0|0|0|0|0|0|0|100|0|0|0|0|0|0|0|0|0|0|100|0|0|0|0|0|0|0|0|0|0|100|0|0|0|0|0|0|0|0|0|0|100|0|0|0|0|0|0|0|0|0|0|0|100|0|0|0|0|0|0|0|0|0|0|100|0|0|0|0|0|0|0|0|0|0|100|0|0|0|0|0|0|0|0|0|0|100|0|0|0|0|0|0|0|0|0|0|100|0|0|0|0|0|0|0|0|0|0|100|0|0|0|0|0|0|0|0|0|0|100|0|0|0|0|0|0|0|0|0|0|100|0|0|0|0|0|0|0|0|0|0|100|0|0|0|0|0|0|0|0|0|0|100|0|0|0|0|0|0|0|0|0|0|100|0|0|0|0|0|0|0|0|0|0|100|0|0|0|0|0|0|0|0|0|0|100|0|0|0|0|0|0|0|0|0|0|100|0|0|0|0|0|0|0|0|0|100|0|0|0|0|0|0|0|0|0|0|100|0|0|0|0|0|0|0|0|0|0|100|0|0|0|0|0|0|0|0|0|0|100|0|0|0|0|0|0|0|0|0|100|0|0|0|0|0|0|0|0|0|0|100|0|0|0|0|0|0|0|0|0|0|100|0|0|0|0|0|0|0|0|0|100|0|0|0|0|0|0|0|0|0|0|100|0|0|0|0|0|0|0|0|0|0|100|0|0|0|0|0|0|0|0|0|100|0|0|0|0|0|0|0|0|0|0|100|0|0|0|0|0|0|0|0|0|100|0|0|0|0|0|0|0|0|0|0|100|0|0|0|0|0|0|0|0|0|100|0|0|0|0|0|0|0|0|0|100|0|0|0|0|0|0|0|0|0|0|100|0|0|0|0|0|0|0|0|0|100|0|0|0|0|0|0|0|0|0|0|100|0|0|0|0|0|0|0|0|0|100|0|0|0|0|0|0|0|0|0|100|0|0|0|0|0|0|0|0|0|100|0|0|0|0|0|0|0|0|0|0|100|0|0|0|0|0|0|0|0|0|100|0|0|0|0|0|0|0|0|0|100|0|0|0|0|0|0|0|0|0|100|0|0|0|0|0|0|0|0|0|100|0|0|0|0|0|0|0|0|0|100|0|0|0|0|0|0|0|0|0|100|0|0|0|0|0|0|0|0|0|100|0|0|0|0|0|0|0|0|0|100|0|0|0|0|0|0|0|0|0|100|0|0|0|0|0|0|0|0|0|100|0|0|0|0|0|0|0|0|0|100|0|0|0|0|0|0|0|0|0|100|0|0|0|0|0|0|0|0|0|100|0|0|0|0|0|0|0|0|0|100|0|0|0|0|0|0|0|0|0|100|0|0|0|0|0|0|0|0|0|100|0|0|0|0|0|0|0|0|100|0|0|0|0|0|0|0|0|0|100|0|0|0|0|0|0|0|0|0|100|0|0|0|0|0|0|0|0|0|100|0|0|0|0|0|0|0|0|100|0|0|0|0|0|0|0|0|0|100|0|0|0|0|0|0|0|0|100|0|0|0|0|0|0|0|0|0|100|0|0|0|0|0|0|0|0|0|100|0|0|0|0|0|0|0|0|100|0|0|0|0|0|0|0|0|0|100|0|0|0|0|0|0|0|0|100|0|0|0|0|0|0|0|0|0|100|0|0|0|0|0|0|0|0|100|0|0|0|0|0|0|0|0|100|0|0|0|0|0|0|0|0|0|100|0|0|0|0|0|0|0|0|100|0|0|0|0|0|0|0|0|100|0|0|0|0|0|0|0|0|0|100|0|0|0|0|0|0|0|0|100|0|0|0|0|0|0|0|0|100|0|0|0|0|0|0|0|0|100|0|0|0|0|0|0|0|0|0|100|0|0|0|0|0|0|0|0|100|0|0|0|0|0|0|0|0|100|0|0|0|0|0|0|0|0|100|0|0|0|0|0|0|0|0|100|0|0|0|0|0|0|0|0|100|0|0|0|0|0|0|0|0|100|0|0|0|0|0|0|0|0|100|0|0|0|0|0|0|0|0|100|0|0|0|0|0|0|0|0|100|0|0|0|0|0|0|0|0|100|0|0|0|0|0|0|0|0|100|0|0|0|0|0|0|0|0|100|0|0|0|0|0|0|0|100|0|0|0|0|0|0|0|0|100|0|0|0|0|0|0|0|0|100</HistCounts>
      </HistItem>
    </Histograms>
    <Metadata>
      <MDI key="STATISTICS_MAXIMUM">36.593770457559</MDI>
      <MDI key="STATISTICS_MEAN">36.104543393338</MDI>
      <MDI key="STATISTICS_MINIMUM">35.570986260293</MDI>
      <MDI key="STATISTICS_STDDEV">0.29843107576564</MDI>
    </Metadata>
  </PAMRasterBand>
</PAMDataset>
